{
  "type": "itemTurret",
  "name": "碎叶炮",
  "description": "中型炮台，对空射击，发射可分裂的小罐茶.",
  "health": 980,
  "size": 2,
  "reload": 5,
  "range": 160,
  "recoil": 2,
  "xRand": 2,
  "inaccuracy": 6,
  "shootShake": 2,
  "rotatespeed": 10,
  "targetGround": false
  "shootSound": "shoot",
  "ammoUseEffect": "shellEjectMedium"
  "ammo": {
    "小罐茶": {
      "speed": 5.5,
      "damage": 10,
      "splashDamageRadius": 30,
      "splashDamage": 30,
      "knockback": 0,
      "fragBullets": 3,
      "fragBullet": {
        "speed": 4,
        "damage": 0,
        "splashDamageRadius": 20,
        "splashDamage": 20,
        "lifetime": 8,
        "bulletWidth": 13,
        "bulletHeight": 10,
        "bulletShrink": 0.9,
        "backColor": "#C5E1A5",
        "frontColor": "#AED581"
        "hitEffect": "formsmoke",
        "collides": true,
        "keepVelocity": true
      },
      "bulletWidth": 9,
      "bulletHeight": 10,
      "shootEffect": "shootBig",
      "smokeEffect": "formsmoke",
      "hitEffect": "plasticExplosion",
      "ammoMultiplier": 5,
      "lifetime": 30,
      "collides": true,
      "keepVelocity": true,
      "backColor": "#C5E1A5",
      "frontColor": "#AED581"
    }
  },
  "requirements": [
    {
      "item": "铝",
      "amount": 80
    },
    {
      "item": "titanium",
      "amount": 75
    },
    {
      "item": "silicon",
      "amount": 45
    }
  ],
  "category": "turret",
  "research": "scatter"
}
